PyAPKDownloader/__init__.py
PyAPKDownloader/apkdownloadertools.py
PyAPKDownloader/apkpure.py
PyAPKDownloader/aptoide.py
PyAPKDownloader-0.0.2.dist-info/METADATA
PyAPKDownloader-0.0.2.dist-info/WHEEL
PyAPKDownloader-0.0.2.dist-info/top_level.txt
PyAPKDownloader-0.0.2.dist-info/RECORD
