Metadata-Version: 2.1
Name: PyAPKDownloader
Version: 0.0.2
Summary: Apk Downloader is a Python module that allows you to download Android APK files using alternative sources such as Aptoide and ApkPure.
Home-page: UNKNOWN
Author: 09u2h4n
Author-email: 09u2h4n.y1lm42@gmail.com
License: UNKNOWN
Project-URL: Source Code, https://github.com/09u2h4n/pyapks
Project-URL: Author's Github, https://github.com/09u2h4n
Platform: UNKNOWN
Requires-Dist: bs4
Requires-Dist: requests
Requires-Dist: tqdm
